annlib
annlib_adaptbx
boost_adaptbx
ccp4io
ccp4io_adaptbx
cctbx
cctbx_website
chiltbx
cma_es
crys3d
dummy
fable
gltbx
gui_resources
iotbx
libtbx
mmtbx
omptbx
rstbx
scitbx
serialtbx
smtbx
spotfinder
tbxx
ucif
wxtbx
